fast_json.py
fast_json-0.3.0.dist-info/DESCRIPTION.rst
fast_json-0.3.0.dist-info/METADATA
fast_json-0.3.0.dist-info/RECORD
fast_json-0.3.0.dist-info/WHEEL
fast_json-0.3.0.dist-info/metadata.json
fast_json-0.3.0.dist-info/top_level.txt
